task3/ramdualport.sv
module ramdualport #(
    parameter   ADDRESS_WIDTH = 9,
                DATA_WIDTH = 9
)(

    input logic clk,
    input logic wr,
    input logic rd,
    input logic [ADDRESS_WIDTH-1:0] wr_addr,
    input logic [ADDRESS_WIDTH-1:0] rd_addr,
    input logic [DATA_WIDTH-1:0] din, 
    output logic [DATA_WIDTH-1:0] dout
);

logic [DATA_WIDTH-1:0] ram_array [2**ADDRESS_WIDTH-1:0];

always_ff @(posedge clk) begin
    if(rd)
        
        dout <= ram_array[rd_addr]; 
    if(wr) 
        
        ram_array[wr_addr] <= din;
end
endmodule

task3/counter.sv
module counter #(
    parameter WIDTH = 9
)(
    input logic clk,
    input logic rst,
    input logic en,
    input logic [WIDTH-1:0] incr,
    output logic [WIDTH-1:0] addr1
);

always_ff @ (posedge clk)
    if(rst) 
        addr1<= {WIDTH{1'b0}};
    
    else  
        addr1 <= addr1 + {{WIDTH-1{1'b0}}, en};
    

endmodule

task3/sigdelay.sv
module sigdelay #(

    parameter   ADDRESS_WIDTH = 9,
                DATA_WIDTH = 9
)(
    
    input logic clk,
    input logic rst,
    input logic wr,             
    input logic rd,
    input logic [DATA_WIDTH-1:0] mic_signal,
    input logic [ADDRESS_WIDTH-1:0] offset,
    input logic [ADDRESS_WIDTH-1:0] incr,
    output logic [DATA_WIDTH-1:0] delayed_signal
);

    logic [ADDRESS_WIDTH-1:0] addr1, wr_addr, rd_addr;
    logic [DATA_WIDTH-1:0] din, dout;

counter counter(

    .clk (clk),
    .rst (rst),
    .en (en),
    .incr (incr),
    .addr1 (addr1)
);

ramdualport ramdualport(

    .clk (clk),
    .wr (wr),
    .rd (rd),
    .rd_addr (rd_addr),
    .wr_addr (wr_addr),
    .dout (dout),
    .din (din)
);

always_ff @ (posedge clk)   begin
    if (rst) begin
        
        wr_addr <= {ADDRESS_WIDTH{1'b0}};
        rd_addr <= {ADDRESS_WIDTH{1'b0}};
    end
    else begin

        if (wr)
        wr_addr <= wr_addr + {{ADDRESS_WIDTH-1{1'b0}}, 1'b1};
        if (rd)
        rd_addr <= wr_addr - offset;
    end
end

always_ff @ (posedge clk) begin
    din <= mic_signal;
    delayed_signal <= dout;
    
end

endmodule

task3/sigdelay.vcd
$version Generated by VerilatedVcd $end
$date Fri Oct 25 11:49:25 2024 $end
$timescale 1ps $end

 $scope module TOP $end
  $var wire  1 ( clk $end
  $var wire  9 / delayed_signal [8:0] $end
  $var wire  9 . incr [8:0] $end
  $var wire  9 , mic_signal [8:0] $end
  $var wire  9 - offset [8:0] $end
  $var wire  1 + rd $end
  $var wire  1 ) rst $end
  $var wire  1 * wr $end
  $scope module sigdelay $end
   $var wire 32 0 ADDRESS_WIDTH [31:0] $end
   $var wire 32 0 DATA_WIDTH [31:0] $end
   $var wire  9 # addr1 [8:0] $end
   $var wire  1 ( clk $end
   $var wire  9 / delayed_signal [8:0] $end
   $var wire  9 & din [8:0] $end
   $var wire  9 ' dout [8:0] $end
   $var wire  1 1 en $end
   $var wire  9 . incr [8:0] $end
   $var wire  9 , mic_signal [8:0] $end
   $var wire  9 - offset [8:0] $end
   $var wire  1 + rd $end
   $var wire  9 % rd_addr [8:0] $end
   $var wire  1 ) rst $end
   $var wire  1 * wr $end
   $var wire  9 $ wr_addr [8:0] $end
   $scope module counter $end
    $var wire 32 0 WIDTH [31:0] $end
    $var wire  9 # addr1 [8:0] $end
    $var wire  1 ( clk $end
    $var wire  1 1 en $end
    $var wire  9 . incr [8:0] $end
    $var wire  1 ) rst $end
   $upscope $end
   $scope module ramdualport $end
    $var wire 32 0 ADDRESS_WIDTH [31:0] $end
    $var wire 32 0 DATA_WIDTH [31:0] $end
    $var wire  1 ( clk $end
    $var wire  9 & din [8:0] $end
    $var wire  9 ' dout [8:0] $end
    $var wire  1 + rd $end
    $var wire  9 % rd_addr [8:0] $end
    $var wire  1 * wr $end
    $var wire  9 $ wr_addr [8:0] $end
   $upscope $end
  $upscope $end
 $upscope $end
$enddefinitions $end


#0
b000000000 #
b000000000 $
b000000000 %
b000000000 &
b000000000 '
1(
0)
1*
1+
b000000000 ,
b001000000 -
b000000000 .
b000000000 /
b00000000000000000000000000001001 0
01
#1
0(
#2
b000000001 $
b111000000 %
1(
b001110010 ,
b000110011 -
#3
0(
#4
b000000010 $
b111001110 %
b001110010 &
1(
#5
0(
#6
b000000011 $
b111001111 %
1(
b001101101 ,
#7
0(
#8
b000000100 $
b111010000 %
b001101101 &
1(
b001101110 ,
#9
0(
#10
b000000101 $
b111010001 %
b001101110 &
1(
b001101011 ,
#11
0(
#12
b000000110 $
b111010010 %
b001101011 &
1(
#13
0(
#14
b000000111 $
b111010011 %
1(
b001101100 ,
#15
0(
#16
b000001000 $
b111010100 %
b001101100 &
1(
b001110000 ,
#17
0(
#18
b000001001 $
b111010101 %
b001110000 &
1(
#19
0(
#20
b000001010 $
b111010110 %
1(
b001110010 ,
#21
0(
#22
b000001011 $
b111010111 %
b001110010 &
1(
b001101001 ,
#23
0(
#24
b000001100 $
b111011000 %
b001101001 &
1(
b001101110 ,
#25
0(
#26
b000001101 $
b111011001 %
b001101110 &
1(
b001101011 ,
#27
0(
#28
b000001110 $
b111011010 %
b001101011 &
1(
#29
0(
#30
b000001111 $
b111011011 %
1(
b001100101 ,
#31
0(
#32
b000010000 $
b111011100 %
b001100101 &
1(
#33
0(
#34
b000010001 $
b111011101 %
1(
b001101001 ,
#35
0(
#36
b000010010 $
b111011110 %
b001101001 &
1(
b001100110 ,
#37
0(
#38
b000010011 $
b111011111 %
b001100110 &
1(
b001101000 ,
#39
0(
#40
b000010100 $
b111100000 %
b001101000 &
1(
b001101110 ,
#41
0(
#42
b000010101 $
b111100001 %
b001101110 &
1(
b001101101 ,
#43
0(
#44
b000010110 $
b111100010 %
b001101101 &
1(
b001101100 ,
#45
0(
#46
b000010111 $
b111100011 %
b001101100 &
1(
b001101111 ,
#47
0(
#48
b000011000 $
b111100100 %
b001101111 &
1(
b001111000 ,
#49
0(
#50
b000011001 $
b111100101 %
b001111000 &
1(
b001110010 ,
#51
0(
#52
b000011010 $
b111100110 %
b001110010 &
1(
b001110001 ,
#53
0(
#54
b000011011 $
b111100111 %
b001110001 &
1(
b001101111 ,
#55
0(
#56
b000011100 $
b111101000 %
b001101111 &
1(
b001101100 ,
#57
0(
#58
b000011101 $
b111101001 %
b001101100 &
1(
b001101000 ,
#59
0(
#60
b000011110 $
b111101010 %
b001101000 &
1(
b001100011 ,
#61
0(
#62
b000011111 $
b111101011 %
b001100011 &
1(
b001100111 ,
#63
0(
#64
b000100000 $
b111101100 %
b001100111 &
1(
#65
0(
#66
b000100001 $
b111101101 %
1(
b001101000 ,
#67
0(
#68
b000100010 $
b111101110 %
b001101000 &
1(
b001100111 ,
#69
0(
#70
b000100011 $
b111101111 %
b001100111 &
1(
b001101011 ,
#71
0(
#72
b000100100 $
b111110000 %
b001101011 &
1(
b001101001 ,
#73
0(
#74
b000100101 $
b111110001 %
b001101001 &
1(
b001101110 ,
#75
0(
#76
b000100110 $
b111110010 %
b001101110 &
1(
b001100111 ,
#77
0(
#78
b000100111 $
b111110011 %
b001100111 &
1(
b001101110 ,
#79
0(
#80
b000101000 $
b111110100 %
b001101110 &
1(
b001101011 ,
#81
0(
#82
b000101001 $
b111110101 %
b001101011 &
1(
b001101110 ,
#83
0(
#84
b000101010 $
b111110110 %
b001101110 &
1(
b001101100 ,
#85
0(
#86
b000101011 $
b111110111 %
b001101100 &
1(
b001110111 ,
#87
0(
#88
b000101100 $
b111111000 %
b001110111 &
1(
b001110100 ,
#89
0(
#90
b000101101 $
b111111001 %
b001110100 &
1(
b001110101 ,
#91
0(
#92
b000101110 $
b111111010 %
b001110101 &
1(
b001110011 ,
#93
0(
#94
b000101111 $
b111111011 %
b001110011 &
1(
b001111000 ,
#95
0(
#96
b000110000 $
b111111100 %
b001111000 &
1(
b001111010 ,
#97
0(
#98
b000110001 $
b111111101 %
b001111010 &
1(
b001111110 ,
#99
0(
#100
b000110010 $
b111111110 %
b001111110 &
1(
b001110110 ,
#101
0(
#102
b000110011 $
b111111111 %
b001110110 &
1(
b001111000 ,
#103
0(
#104
b000110100 $
b000000000 %
b001111000 &
1(
b001110111 ,
#105
0(
#106
b000110101 $
b000000001 %
b001110111 &
1(
#107
0(
#108
b000110110 $
b000000010 %
1(
#109
0(
#110
b000110111 $
b000000011 %
b001110010 '
1(
b001110001 ,
#111
0(
#112
b000111000 $
b000000100 %
b001110001 &
1(
b001111000 ,
b001110010 /
#113
0(
#114
b000111001 $
b000000101 %
b001111000 &
b001101101 '
1(
b001111011 ,
#115
0(
#116
b000111010 $
b000000110 %
b001111011 &
b001101110 '
1(
b001111001 ,
b001101101 /
#117
0(
#118
b000111011 $
b000000111 %
b001111001 &
b001101011 '
1(
b001110000 ,
b001101110 /
#119
0(
#120
b000111100 $
b000001000 %
b001110000 &
1(
b001101110 ,
b001101011 /
#121
0(
#122
b000111101 $
b000001001 %
b001101110 &
b001101100 '
1(
#123
0(
#124
b000111110 $
b000001010 %
b001110000 '
1(
b001101100 /
#125
0(
#126
b000111111 $
b000001011 %
1(
b001100111 ,
b001110000 /
#127
0(
#128
b001000000 $
b000001100 %
b001100111 &
b001110010 '
1(
b001101000 ,
#129
0(
#130
b001000001 $
b000001101 %
b001101000 &
b001101001 '
1(
b001110010 /
#131
0(
#132
b001000010 $
b000001110 %
b001101110 '
1(
b001101011 ,
b001101001 /
#133
0(
#134
b001000011 $
b000001111 %
b001101011 &
b001101011 '
1(
b001100010 ,
b001101110 /
#135
0(
#136
b001000100 $
b000010000 %
b001100010 &
1(
b001100011 ,
b001101011 /
#137
0(
#138
b001000101 $
b000010001 %
b001100011 &
b001100101 '
1(
b001100010 ,
#139
0(
#140
b001000110 $
b000010010 %
b001100010 &
1(
b001101010 ,
b001100101 /
#141
0(
#142
b001000111 $
b000010011 %
b001101010 &
b001101001 '
1(
b001100111 ,
#143
0(
#144
b001001000 $
b000010100 %
b001100111 &
b001100110 '
1(
b001101100 ,
b001101001 /
#145
0(
#146
b001001001 $
b000010101 %
b001101100 &
b001101000 '
1(
b001101011 ,
b001100110 /
#147
0(
#148
b001001010 $
b000010110 %
b001101011 &
b001101110 '
1(
b001101101 ,
b001101000 /
#149
0(
#150
b001001011 $
b000010111 %
b001101101 &
b001101101 '
1(
b001101110 ,
b001101110 /
#151
0(
#152
b001001100 $
b000011000 %
b001101110 &
b001101100 '
1(
b001101011 ,
b001101101 /
#153
0(
#154
b001001101 $
b000011001 %
b001101011 &
b001101111 '
1(
b001100111 ,
b001101100 /
#155
0(
#156
b001001110 $
b000011010 %
b001100111 &
b001111000 '
1(
b001101101 ,
b001101111 /
#157
0(
#158
b001001111 $
b000011011 %
b001101101 &
b001110010 '
1(
b001101001 ,
b001111000 /
#159
0(
#160
b001010000 $
b000011100 %
b001101001 &
b001110001 '
1(
b001101111 ,
b001110010 /
#161
0(
#162
b001010001 $
b000011101 %
b001101111 &
b001101111 '
1(
b001110001 /
#163
0(
#164
b001010010 $
b000011110 %
b001101100 '
1(
b001110001 ,
b001101111 /
#165
0(
#166
b001010011 $
b000011111 %
b001110001 &
b001101000 '
1(
b001101101 ,
b001101100 /
#167
0(
#168
b001010100 $
b000100000 %
b001101101 &
b001100011 '
1(
b001101011 ,
b001101000 /
#169
0(
#170
b001010101 $
b000100001 %
b001101011 &
b001100111 '
1(
b001100011 /
#171
0(
#172
b001010110 $
b000100010 %
1(
b001100111 ,
b001100111 /
#173
0(
#174
b001010111 $
b000100011 %
b001100111 &
b001101000 '
1(
b001101010 ,
#175
0(
#176
b001011000 $
b000100100 %
b001101010 &
b001100111 '
1(
b001101110 ,
b001101000 /
#177
0(
#178
b001011001 $
b000100101 %
b001101110 &
b001101011 '
1(
b001110100 ,
b001100111 /
#179
0(
#180
b001011010 $
b000100110 %
b001110100 &
b001101001 '
1(
b001110000 ,
b001101011 /
#181
0(
#182
b001011011 $
b000100111 %
b001110000 &
b001101110 '
1(
b001110001 ,
b001101001 /
#183
0(
#184
b001011100 $
b000101000 %
b001110001 &
b001100111 '
1(
b001110100 ,
b001101110 /
#185
0(
#186
b001011101 $
b000101001 %
b001110100 &
b001101110 '
1(
b001110111 ,
b001100111 /
#187
0(
#188
b001011110 $
b000101010 %
b001110111 &
b001101011 '
1(
b001110010 ,
b001101110 /
#189
0(
#190
b001011111 $
b000101011 %
b001110010 &
b001101110 '
1(
b001111000 ,
b001101011 /
#191
0(
#192
b001100000 $
b000101100 %
b001111000 &
b001101100 '
1(
b001111001 ,
b001101110 /
#193
0(
#194
b001100001 $
b000101101 %
b001111001 &
b001110111 '
1(
b001111010 ,
b001101100 /
#195
0(
#196
b001100010 $
b000101110 %
b001111010 &
b001110100 '
1(
b001110110 ,
b001110111 /
#197
0(
#198
b001100011 $
b000101111 %
b001110110 &
b001110101 '
1(
b001111000 ,
b001110100 /
#199
0(
#200
b001100100 $
b000110000 %
b001111000 &
b001110011 '
1(
b001110101 ,
b001110101 /
#201
0(
#202
b001100101 $
b000110001 %
b001110101 &
b001111000 '
1(
b001110010 ,
b001110011 /
#203
0(
#204
b001100110 $
b000110010 %
b001110010 &
b001111010 '
1(
b001110011 ,
b001111000 /
#205
0(
#206
b001100111 $
b000110011 %
b001110011 &
b001111110 '
1(
b001110111 ,
b001111010 /
#207
0(
#208
b001101000 $
b000110100 %
b001110111 &
b001110110 '
1(
b001110101 ,
b001111110 /
#209
0(
#210
b001101001 $
b000110101 %
b001110101 &
b001111000 '
1(
b001110110 /
#211
0(
#212
b001101010 $
b000110110 %
b001110111 '
1(
b001110000 ,
b001111000 /
#213
0(
#214
b001101011 $
b000110111 %
b001110000 &
1(
b001101101 ,
b001110111 /
#215
0(
#216
b001101100 $
b000111000 %
b001101101 &
1(
b001101011 ,
#217
0(
#218
b001101101 $
b000111001 %
b001101011 &
b001110001 '
1(
b001101100 ,
#219
0(
#220
b001101110 $
b000111010 %
b001101100 &
b001111000 '
1(
b001101001 ,
b001110001 /
#221
0(
#222
b001101111 $
b000111011 %
b001101001 &
b001111011 '
1(
b001100101 ,
b001111000 /
#223
0(
#224
b001110000 $
b000111100 %
b001100101 &
b001111001 '
1(
b001101000 ,
b001111011 /
#225
0(
#226
b001110001 $
b000111101 %
b001101000 &
b001110000 '
1(
b001101001 ,
b001111001 /
#227
0(
#228
b001110010 $
b000111110 %
b001101001 &
b001101110 '
1(
b001110000 /
#229
0(
#230
b001110011 $
b000111111 %
1(
b001011101 ,
b001101110 /
#231
0(
#232
b001110100 $
b001000000 %
b001011101 &
1(
b001011011 ,
#233
0(
#234
b001110101 $
b001000001 %
b001011011 &
b001100111 '
1(
b001011111 ,
#235
0(
#236
b001110110 $
b001000010 %
b001011111 &
b001101000 '
1(
b001100001 ,
b001100111 /
#237
0(
#238
b001110111 $
b001000011 %
b001100001 &
1(
b001101000 /
#239
0(
#240
b001111000 $
b001000100 %
b001101011 '
1(
#241
0(
#242
b001111001 $
b001000101 %
b001100010 '
1(
b001100011 ,
b001101011 /
#243
0(
#244
b001111010 $
b001000110 %
b001100011 &
b001100011 '
1(
b001100010 /
#245
0(
#246
b001111011 $
b001000111 %
b001100010 '
1(
b001100101 ,
b001100011 /
#247
0(
#248
b001111100 $
b001001000 %
b001100101 &
b001101010 '
1(
b001100110 ,
b001100010 /
#249
0(
#250
b001111101 $
b001001001 %
b001100110 &
b001100111 '
1(
b001101010 /
#251
0(
#252
b001111110 $
b001001010 %
b001101100 '
1(
b001101001 ,
b001100111 /
#253
0(
#254
b001111111 $
b001001011 %
b001101001 &
b001101011 '
1(
b001101100 /
#255
0(
#256
b010000000 $
b001001100 %
b001101101 '
1(
b001101000 ,
b001101011 /
#257
0(
#258
b010000001 $
b001001101 %
b001101000 &
b001101110 '
1(
b001101001 ,
b001101101 /
#259
0(
#260
b010000010 $
b001001110 %
b001101001 &
b001101011 '
1(
b001101110 /
#261
0(
#262
b010000011 $
b001001111 %
b001100111 '
1(
b001101100 ,
b001101011 /
#263
0(
#264
b010000100 $
b001010000 %
b001101100 &
b001101101 '
1(
b001101010 ,
b001100111 /
#265
0(
#266
b010000101 $
b001010001 %
b001101010 &
b001101001 '
1(
b001101011 ,
b001101101 /
#267
0(
#268
b010000110 $
b001010010 %
b001101011 &
b001101111 '
1(
b001101000 ,
b001101001 /
#269
0(
#270
b010000111 $
b001010011 %
b001101000 &
1(
b001101011 ,
b001101111 /
#271
0(
#272
b010001000 $
b001010100 %
b001101011 &
b001110001 '
1(
b001101101 ,
#273
0(
#274
b010001001 $
b001010101 %
b001101101 &
b001101101 '
1(
b001110001 /
#275
0(
#276
b010001010 $
b001010110 %
b001101011 '
1(
b001101000 ,
b001101101 /
#277
0(
#278
b010001011 $
b001010111 %
b001101000 &
1(
b001100101 ,
b001101011 /
#279
0(
#280
b010001100 $
b001011000 %
b001100101 &
b001100111 '
1(
b001101011 ,
#281
0(
#282
b010001101 $
b001011001 %
b001101011 &
b001101010 '
1(
b001101001 ,
b001100111 /
#283
0(
#284
b010001110 $
b001011010 %
b001101001 &
b001101110 '
1(
b001101010 /
#285
0(
#286
b010001111 $
b001011011 %
b001110100 '
1(
b001101011 ,
b001101110 /
#287
0(
#288
b010010000 $
b001011100 %
b001101011 &
b001110000 '
1(
b001101101 ,
b001110100 /
#289
0(
#290
b010010001 $
b001011101 %
b001101101 &
b001110001 '
1(
b001101011 ,
b001110000 /
#291
0(
#292
b010010010 $
b001011110 %
b001101011 &
b001110100 '
1(
b001101001 ,
b001110001 /
#293
0(
#294
b010010011 $
b001011111 %
b001101001 &
b001110111 '
1(
b001100101 ,
b001110100 /
#295
0(
#296
b010010100 $
b001100000 %
b001100101 &
b001110010 '
1(
b001100110 ,
b001110111 /
#297
0(
#298
b010010101 $
b001100001 %
b001100110 &
b001111000 '
1(
b001101011 ,
b001110010 /
#299
0(
#300
b010010110 $
b001100010 %
b001101011 &
b001111001 '
1(
b001110000 ,
b001111000 /
#301
0(
#302
b010010111 $
b001100011 %
b001110000 &
b001111010 '
1(
b001101011 ,
b001111001 /
#303
0(
#304
b010011000 $
b001100100 %
b001101011 &
b001110110 '
1(
b001101101 ,
b001111010 /
#305
0(
#306
b010011001 $
b001100101 %
b001101101 &
b001111000 '
1(
b001101010 ,
b001110110 /
#307
0(
#308
b010011010 $
b001100110 %
b001101010 &
b001110101 '
1(
b001101000 ,
b001111000 /
#309
0(
#310
b010011011 $
b001100111 %
b001101000 &
b001110010 '
1(
b001100111 ,
b001110101 /
#311
0(
#312
b010011100 $
b001101000 %
b001100111 &
b001110011 '
1(
b001100110 ,
b001110010 /
#313
0(
#314
b010011101 $
b001101001 %
b001100110 &
b001110111 '
1(
b001101010 ,
b001110011 /
#315
0(
#316
b010011110 $
b001101010 %
b001101010 &
b001110101 '
1(
b001101101 ,
b001110111 /
#317
0(
#318
b010011111 $
b001101011 %
b001101101 &
1(
b001110001 ,
b001110101 /
#319
0(
#320
b010100000 $
b001101100 %
b001110001 &
b001110000 '
1(
b001111000 ,
#321
0(
#322
b010100001 $
b001101101 %
b001111000 &
b001101101 '
1(
b001110100 ,
b001110000 /
#323
0(
#324
b010100010 $
b001101110 %
b001110100 &
b001101011 '
1(
b001110010 ,
b001101101 /
#325
0(
#326
b010100011 $
b001101111 %
b001110010 &
b001101100 '
1(
b001110011 ,
b001101011 /
#327
0(
#328
b010100100 $
b001110000 %
b001110011 &
b001101001 '
1(
b001110001 ,
b001101100 /
#329
0(
#330
b010100101 $
b001110001 %
b001110001 &
b001100101 '
1(
b001101100 ,
b001101001 /
#331
0(
#332
b010100110 $
b001110010 %
b001101100 &
b001101000 '
1(
b001101010 ,
b001100101 /
#333
0(
#334
b010100111 $
b001110011 %
b001101010 &
b001101001 '
1(
b001101001 ,
b001101000 /
#335
0(
#336
b010101000 $
b001110100 %
b001101001 &
1(
b001101010 ,
b001101001 /
#337
0(
#338
b010101001 $
b001110101 %
b001101010 &
b001011101 '
1(
b001101001 ,
#339
0(
#340
b010101010 $
b001110110 %
b001101001 &
b001011011 '
1(
b001101000 ,
b001011101 /
#341
0(
#342
b010101011 $
b001110111 %
b001101000 &
b001011111 '
1(
b001100111 ,
b001011011 /
#343
0(
#344
b010101100 $
b001111000 %
b001100111 &
b001100001 '
1(
b001100110 ,
b001011111 /
#345
0(
#346
b010101101 $
b001111001 %
b001100110 &
1(
b001100111 ,
b001100001 /
#347
0(
#348
b010101110 $
b001111010 %
b001100111 &
1(
b001100110 ,
#349
0(
#350
b010101111 $
b001111011 %
b001100110 &
b001100011 '
1(
b001101001 ,
#351
0(
#352
b010110000 $
b001111100 %
b001101001 &
1(
b001100100 ,
b001100011 /
#353
0(
#354
b010110001 $
b001111101 %
b001100100 &
b001100101 '
1(
b001100101 ,
#355
0(
#356
b010110010 $
b001111110 %
b001100101 &
b001100110 '
1(
b001100010 ,
b001100101 /
#357
0(
#358
b010110011 $
b001111111 %
b001100010 &
1(
b001101010 ,
b001100110 /
#359
0(
#360
b010110100 $
b010000000 %
b001101010 &
b001101001 '
1(
#361
0(
#362
b010110101 $
b010000001 %
1(
b001101111 ,
b001101001 /
#363
0(
#364
b010110110 $
b010000010 %
b001101111 &
b001101000 '
1(
b001110100 ,
#365
0(
#366
b010110111 $
b010000011 %
b001110100 &
b001101001 '
1(
b001111011 ,
b001101000 /
#367
0(
#368
b010111000 $
b010000100 %
b001111011 &
1(
b001110011 ,
b001101001 /
#369
0(
#370
b010111001 $
b010000101 %
b001110011 &
b001101100 '
1(
b001110000 ,
#371
0(
#372
b010111010 $
b010000110 %
b001110000 &
b001101010 '
1(
b001101100 /
#373
0(
#374
b010111011 $
b010000111 %
b001101011 '
1(
b001101110 ,
b001101010 /
#375
0(
#376
b010111100 $
b010001000 %
b001101110 &
b001101000 '
1(
b001101011 ,
b001101011 /
#377
0(
#378
b010111101 $
b010001001 %
b001101011 &
b001101011 '
1(
b001110000 ,
b001101000 /
#379
0(
#380
b010111110 $
b010001010 %
b001110000 &
b001101101 '
1(
b001110100 ,
b001101011 /
#381
0(
#382
b010111111 $
b010001011 %
b001110100 &
1(
b001110110 ,
b001101101 /
#383
0(
#384
b011000000 $
b010001100 %
b001110110 &
b001101000 '
1(
b001110011 ,
#385
0(
#386
b011000001 $
b010001101 %
b001110011 &
b001100101 '
1(
b001101000 /
#387
0(
#388
b011000010 $
b010001110 %
b001101011 '
1(
b001110100 ,
b001100101 /
#389
0(
#390
b011000011 $
b010001111 %
b001110100 &
b001101001 '
1(
b001110001 ,
b001101011 /
#391
0(
#392
b011000100 $
b010010000 %
b001110001 &
1(
b001110101 ,
b001101001 /
#393
0(
#394
b011000101 $
b010010001 %
b001110101 &
b001101011 '
1(
b001110010 ,
#395
0(
#396
b011000110 $
b010010010 %
b001110010 &
b001101101 '
1(
b001110100 ,
b001101011 /
#397
0(
#398
b011000111 $
b010010011 %
b001110100 &
b001101011 '
1(
b001110001 ,
b001101101 /
#399
0(
#400
b011001000 $
b010010100 %
b001110001 &
b001101001 '
1(
b001101011 /
#401
0(
#402
b011001001 $
b010010101 %
b001100101 '
1(
b001101011 ,
b001101001 /
#403
0(
#404
b011001010 $
b010010110 %
b001101011 &
b001100110 '
1(
b001101010 ,
b001100101 /
#405
0(
#406
b011001011 $
b010010111 %
b001101010 &
b001101011 '
1(
b001101001 ,
b001100110 /
#407
0(
#408
b011001100 $
b010011000 %
b001101001 &
b001110000 '
1(
b001101011 ,
b001101011 /
#409
0(
#410
b011001101 $
b010011001 %
b001101011 &
b001101011 '
1(
b001101110 ,
b001110000 /
#411
0(
#412
b011001110 $
b010011010 %
b001101110 &
b001101101 '
1(
b001101011 /
#413
0(
#414
b011001111 $
b010011011 %
b001101010 '
1(
b001101101 /
#415
0(
#416
b011010000 $
b010011100 %
b001101000 '
1(
b001110001 ,
b001101010 /
#417
0(
#418
b011010001 $
b010011101 %
b001110001 &
b001100111 '
1(
b001110011 ,
b001101000 /
#419
0(
#420
b011010010 $
b010011110 %
b001110011 &
b001100110 '
1(
b001110010 ,
b001100111 /
#421
0(
#422
b011010011 $
b010011111 %
b001110010 &
b001101010 '
1(
b001100110 /
#423
0(
#424
b011010100 $
b010100000 %
b001101101 '
1(
b001110011 ,
b001101010 /
#425
0(
#426
b011010101 $
b010100001 %
b001110011 &
b001110001 '
1(
b001101111 ,
b001101101 /
#427
0(
#428
b011010110 $
b010100010 %
b001101111 &
b001111000 '
1(
b001110100 ,
b001110001 /
#429
0(
#430
b011010111 $
b010100011 %
b001110100 &
b001110100 '
1(
b001110010 ,
b001111000 /
#431
0(
#432
b011011000 $
b010100100 %
b001110010 &
b001110010 '
1(
b001110011 ,
b001110100 /
#433
0(
#434
b011011001 $
b010100101 %
b001110011 &
b001110011 '
1(
b001110010 ,
b001110010 /
#435
0(
#436
b011011010 $
b010100110 %
b001110010 &
b001110001 '
1(
b001110110 ,
b001110011 /
#437
0(
#438
b011011011 $
b010100111 %
b001110110 &
b001101100 '
1(
b001110001 ,
b001110001 /
#439
0(
#440
b011011100 $
b010101000 %
b001110001 &
b001101010 '
1(
b001110011 ,
b001101100 /
#441
0(
#442
b011011101 $
b010101001 %
b001110011 &
b001101001 '
1(
b001101100 ,
b001101010 /
#443
0(
#444
b011011110 $
b010101010 %
b001101100 &
b001101010 '
1(
b001110010 ,
b001101001 /
#445
0(
#446
b011011111 $
b010101011 %
b001110010 &
b001101001 '
1(
b001101110 ,
b001101010 /
#447
0(
#448
b011100000 $
b010101100 %
b001101110 &
b001101000 '
1(
b001110010 ,
b001101001 /
#449
0(
#450
b011100001 $
b010101101 %
b001110010 &
b001100111 '
1(
b001110000 ,
b001101000 /
#451
0(
#452
b011100010 $
b010101110 %
b001110000 &
b001100110 '
1(
b001101111 ,
b001100111 /
#453
0(
#454
b011100011 $
b010101111 %
b001101111 &
b001100111 '
1(
b001110000 ,
b001100110 /
#455
0(
#456
b011100100 $
b010110000 %
b001110000 &
b001100110 '
1(
b001110001 ,
b001100111 /
#457
0(
#458
b011100101 $
b010110001 %
b001110001 &
b001101001 '
1(
b001100110 /
#459
0(
#460
b011100110 $
b010110010 %
b001100100 '
1(
b001110000 ,
b001101001 /
#461
0(
#462
b011100111 $
b010110011 %
b001110000 &
b001100101 '
1(
b001101111 ,
b001100100 /
#463
0(
#464
b011101000 $
b010110100 %
b001101111 &
b001100010 '
1(
b001110010 ,
b001100101 /
#465
0(
#466
b011101001 $
b010110101 %
b001110010 &
b001101010 '
1(
b001101011 ,
b001100010 /
#467
0(
#468
b011101010 $
b010110110 %
b001101011 &
1(
b001110010 ,
b001101010 /
#469
0(
#470
b011101011 $
b010110111 %
b001110010 &
b001101111 '
1(
b001110000 ,
#471
0(
#472
b011101100 $
b010111000 %
b001110000 &
b001110100 '
1(
b001110011 ,
b001101111 /
#473
0(
#474
b011101101 $
b010111001 %
b001110011 &
b001111011 '
1(
b001101111 ,
b001110100 /
#475
0(
#476
b011101110 $
b010111010 %
b001101111 &
b001110011 '
1(
b001110011 ,
b001111011 /
#477
0(
#478
b011101111 $
b010111011 %
b001110011 &
b001110000 '
1(
b001110101 ,
b001110011 /
#479
0(
#480
b011110000 $
b010111100 %
b001110101 &
1(
b001110010 ,
b001110000 /
#481
0(
#482
b011110001 $
b010111101 %
b001110010 &
b001101110 '
1(
b001110101 ,
#483
0(
#484
b011110010 $
b010111110 %
b001110101 &
b001101011 '
1(
b001110001 ,
b001101110 /
#485
0(
#486
b011110011 $
b010111111 %
b001110001 &
b001110000 '
1(
b001110011 ,
b001101011 /
#487
0(
#488
b011110100 $
b011000000 %
b001110011 &
b001110100 '
1(
b001110100 ,
b001110000 /
#489
0(
#490
b011110101 $
b011000001 %
b001110100 &
b001110110 '
1(
b001101101 ,
b001110100 /
#491
0(
#492
b011110110 $
b011000010 %
b001101101 &
b001110011 '
1(
b001101001 ,
b001110110 /
#493
0(
#494
b011110111 $
b011000011 %
b001101001 &
1(
b001101010 ,
b001110011 /
#495
0(
#496
b011111000 $
b011000100 %
b001101010 &
b001110100 '
1(
b001101110 ,
#497
0(
#498
b011111001 $
b011000101 %
b001101110 &
b001110001 '
1(
b001100111 ,
b001110100 /
#499
0(
#500
b011111010 $
b011000110 %
b001100111 &
b001110101 '
1(
b001100100 ,
b001110001 /
#501
0(
#502
b011111011 $
b011000111 %
b001100100 &
b001110010 '
1(
b001101010 ,
b001110101 /
#503
0(
#504
b011111100 $
b011001000 %
b001101010 &
b001110100 '
1(
b001101000 ,
b001110010 /
#505
0(
#506
b011111101 $
b011001001 %
b001101000 &
b001110001 '
1(
b001100101 ,
b001110100 /
#507
0(
#508
b011111110 $
b011001010 %
b001100101 &
1(
b001100011 ,
b001110001 /
#509
0(
#510
b011111111 $
b011001011 %
b001100011 &
b001101011 '
1(
b001101001 ,
#511
0(
#512
b100000000 $
b011001100 %
b001101001 &
b001101010 '
1(
b001101010 ,
b001101011 /
#513
0(
#514
b100000001 $
b011001101 %
b001101010 &
b001101001 '
1(
b001101011 ,
b001101010 /
#515
0(
#516
b100000010 $
b011001110 %
b001101011 &
b001101011 '
1(
b001101110 ,
b001101001 /
#517
0(
#518
b100000011 $
b011001111 %
b001101110 &
b001101110 '
1(
b001110010 ,
b001101011 /
#519
0(
#520
b100000100 $
b011010000 %
b001110010 &
1(
b001101110 /
#521
0(
#522
b100000101 $
b011010001 %
1(
b001101111 ,
#523
0(
#524
b100000110 $
b011010010 %
b001101111 &
b001110001 '
1(
#525
0(
#526
b100000111 $
b011010011 %
b001110011 '
1(
b001110000 ,
b001110001 /
#527
0(
#528
b100001000 $
b011010100 %
b001110000 &
b001110010 '
1(
b001101111 ,
b001110011 /
#529
0(
